Workbook

Sheet Raw Data
A1: Tata Consumer Products Ltd.
A3: Historical Financial Performance & Balance Sheet Extracts (FY22 – FY26)
A4: (Source: Annual Reports / Screener.in)
A5: Particulars(Rs. In Cr) | B5: FY 2022 | C5: FY 2023 | D5: FY 2024 | E5: FY 2025 | F5: FY 2026
A6: Sales(Revenue) | B6: 12425 | C6: 13783 | D6: 15206 | E6: 17618 | F6: 20290
A7: Expenses | B7: 10707 | C7: 11927 | D7: 12922 | E7: 15139 | F7: 17499
A8: Interest | B8: 73 | C8: 87 | D8: 130 | E8: 290 | F8: 137
A9: Depreciation | B9: 278 | C9: 304 | D9: 377 | E9: 377 | F9: 627
A10: Operating Profits | B10: 1719 | C10: 1856 | D10: 2284 | E10: 2479 | F10: 2792
A11: Profit before tax | B11: 1456 | C11: 1794 | D11: 1696 | E11: 1777 | F11: 2173
A12: Net Profit | B12: 1015 | C12: 1320 | D12: 1215 | E12: 1287 | F12: 1547
A13: Equity Capital | B13: 92 | C13: 93 | D13: 95 | E13: 99 | F13: 99
A14: Reserves | B14: 15050 | C14: 16184 | D14: 15962 | E14: 19902 | F14: 21689
A15: Borrowings | B15: 1412 | C15: 1600 | D15: 3477 | E15: 2393 | F15: 2393
A16: Total Liabilities | B16: 21075 | C16: 22762 | D16: 27879 | E16: 31831 | F16: 34279
A17: Total Assets | B17: 21075 | C17: 22762 | D17: 27879 | E17: 31831 | F17: 34279
... A23: Trade Payables | B23: 1916 | C23: 2348 | D23: 2707 | E23: 3508 | F23: 3875

Sheet Financial Ratios
A1: Financial Ratios
A2: Ratio | C2: FY 2022 | D2: FY 2023 | E2: FY 2024 | F2: FY 2025 | G2: FY 2026
A3: Profitability | B3: Operating Profit Margin(OPM) | C3: ='Raw Data'!B10/'Raw Data'!B6 -> 0.1383501 | D3: ='Raw Data'!C10/'Raw Data'!C6 -> 0.13465864 | E3: ='Raw Data'!D10/'Raw Data'!D6 -> 0.15020387 | F3: ='Raw Data'!E10/'Raw Data'!E6 -> 0.14070837 | G3: ='Raw Data'!F10/'Raw Data'!F6 -> 0.13760473 | I3: OPM=Operating profit/ Sales
B4: Net Profit Margin(NPM) | C4: ='Raw Data'!B12/'Raw Data'!B6 -> 0.081690141 | D4: ='Raw Data'!C12/'Raw Data'!C6 -> 0.095770152 | E4: ='Raw Data'!D12/'Raw Data'!D6 -> 0.07990267 | F4: ='Raw Data'!E12/'Raw Data'!E6 -> 0.073050289 | G4: ='Raw Data'!F12/'Raw Data'!F6 -> 0.076244455 | I4: NPM=Net profit/Sales
B5: Return on Equity(ROE) | C5: =('Raw Data'!B12)/('Raw Data'!B13+'Raw Data'!B14) -> 0.067032096 | D5: ='Raw Data'!C12/('Raw Data'!C13+'Raw Data'!C14) -> 0.081096025 | E5: ='Raw Data'!D12/('Raw Data'!D13+'Raw Data'!D14) -> 0.075667933 | F5: ='Raw Data'!E12/('Raw Data'!E13+'Raw Data'!E14) -> 0.064346783 | G5: ='Raw Data'!F12/('Raw Data'!F13+'Raw Data'!F14) -> 0.071002387 | I5: ROE=Net profit)/(Equity Capital+Reserves)
A6: Leverage | I6: Debt To Equity Ratio=(Borrowing)/(Equity Capital+Reserves)
B7: Debt To Equity Ratio | C7: =('Raw Data'!B15)/('Raw Data'!B13+'Raw Data'!B14) -> 0.093250561 | D7: =('Raw Data'!C15)/('Raw Data'!C13+'Raw Data'!C14) -> 0.098298212 | E7: =('Raw Data'!D15)/('Raw Data'!D13+'Raw Data'!D14) -> 0.21654107 | F7: =('Raw Data'!E15)/('Raw Data'!E13+'Raw Data'!E14) -> 0.11964402 | G7: =('Raw Data'!F15)/('Raw Data'!F13+'Raw Data'!F14) -> 0.1098311 | I7: Interset Coverage Ratio=operating profits/Interest
B8: Interest Coverage Ratio | C8: ='Raw Data'!B10/'Raw Data'!B8 -> 23.547945 | D8: ='Raw Data'!C10/'Raw Data'!C8 -> 21.333333 | E8: ='Raw Data'!D10/'Raw Data'!D8 -> 17.569231 | F8: ='Raw Data'!E10/'Raw Data'!E8 -> 8.5482759 | G8: ='Raw Data'!F10/'Raw Data'!F8 -> 20.379562 | I8: Current Ratio=(Receivables+Inventory+Cash)/(Trade Payables)
A9: Liquidity | I9: Quick Ratio=(Trade receivables+Cash)/(Trade payables)
B10: Current Ratio | C10: =('Raw Data'!B19+'Raw Data'!B20+'Raw Data'!B21)/('Raw Data'!B23) -> 2.9759916 | D10: =('Raw Data'!C19+'Raw Data'!C20+'Raw Data'!C21)/('Raw Data'!C23) -> 2.6818569 | E10: =('Raw Data'!D19+'Raw Data'!D20+'Raw Data'!D21)/('Raw Data'!D23) -> 2.2608053 | F10: =('Raw Data'!E19+'Raw Data'!E20+'Raw Data'!E21)/('Raw Data'!E23) -> 2.0775371 | G10: =('Raw Data'!F19+'Raw Data'!F20+'Raw Data'!F21)/('Raw Data'!F23) -> 2.0890323 | I10: Asset Turnover=Sales/Total Assets
B11: Quick Ratio | C11: =('Raw Data'!B19+'Raw Data'!B21)/('Raw Data'!B23) -> 1.7927975 | D11: =('Raw Data'!C19+'Raw Data'!C21)/('Raw Data'!C23) -> 1.5310903 | E11: =('Raw Data'!D19+'Raw Data'!D21)/('Raw Data'!D23) -> 1.2379017 | F11: =('Raw Data'!E19+'Raw Data'!E21)/('Raw Data'!E23) -> 1.0513113 | G11: =('Raw Data'!F19+'Raw Data'!F21)/('Raw Data'!F23) -> 1.1788387 | I11: Inventory Turnover=Expenses/Inventory
A12: Efficiency
B13: Asset Turnover | C13: ='Raw Data'!B6/'Raw Data'!B17 -> 0.58956109 | D13: ='Raw Data'!C6/'Raw Data'!C17 -> 0.60552676 | E13: ='Raw Data'!D6/'Raw Data'!D17 -> 0.54542846 | F13: ='Raw Data'!E6/'Raw Data'!E17 -> 0.5534856 | G13: ='Raw Data'!F6/'Raw Data'!F17 -> 0.59190758
B14: Inventory Turnover | C14: ='Raw Data'!B7/'Raw Data'!B20 -> 4.7229819 | D14: ='Raw Data'!C7/'Raw Data'!C20 -> 4.4141377 | E14: ='Raw Data'!D7/'Raw Data'!D20 -> 4.6666667 | F14: ='Raw Data'!E7/'Raw Data'!E20 -> 4.2052778 | G14: ='Raw Data'!F7/'Raw Data'!F20 -> 4.9614403

Sheet Trend Analysis
A1: Trend Analysis
B18: Key Financial Insights & Observations
B20: • Profitability: Operating profit margin (OPM) held steady between 13% and 15% across all 5 years, reflecting consistent core pricing power. Net profit margin (NPM) peaked at ~10% in FY23 before settling at 7–8%, impacted by higher interest costs in FY25.
B22: • Liquidity: The Current Ratio eased from 2.98x (FY22) to ~2.09x (FY26), while the Quick Ratio adjusted from 1.79x to 1.18x. Both remain well within healthy solvency benchmarks (>1.5x and >1.0x), indicating solid short-term obligations coverage.
B24: • Solvency: Debt-to-Equity remained conservative throughout (0.09x to 0.11x, with a brief uptick to 0.22x in FY24), supported by robust Interest Coverage consistently above 8x, reaching ~20x in FY26.

Sheet Peer Comparison
A1: Fast Moving Consumer Goods Companies (PEER COMPARISON)
A2: Ratio / Metric | B2: Tata Consumer Products Ltd | C2: Hindustan Unilever Ltd | D2: Nestle India Ltd | E2: Britannia Industries Ltd | F2: Godrej Consumer Products Ltd | G2: Dabur India Ltd
A3: Current Market PriceCMP(Rs) | B3: 983.2 | C3: 1942.9 | D3: 1362.6 | E3: 4937.5 | F3: 880 | G3: 385.6
A4: Price to Earning Ratio | B4: 59 | C4: 41.4 | D4: 69.98 | E4: 45.67 | F4: 43.37 | G4: 34.48
A5: Market Capitalisation in Rs(Cr) | B5: 97306.83 | C5: 456502.09 | D5: 262752.11 | E5: 118928.72 | F5: 90050.84 | G5: 68403.78
A6: Dividend Yield(%) | B6: 1.02 | C6: 2.1 | D6: 0.88 | E6: 1.83 | F6: 2.27 | G6: 2.14
A7: Net Profit Quarter in Rs(Cr) | B7: 427.19 | C7: 2680 | D7: 975.12 | E7: 593.38 | F7: 504.52 | G7: 586.16
A12: Peer Valuation Summary: Tata Consumer ranks 5th by Market Capitalization (₹97,306 Cr) among top Indian FMCG peers. It commands a premium multiple of 59.0x P/E—higher than mature peers like HUL (41.4x) and Britannia (45.7x)—reflecting strong market expectations for category expansion, brand strength, and long-term earnings growth toward high-margin leaders like Nestle (69.98x).

Sheet Summary
B1: Tata Consumer Products Ltd
B3: 1. Key Financial Highlights
B4: • Profitability: Operating Profit Margin (OPM) held consistently between 13% and 15%, while Net Profit Margin (NPM) stabilized at 7–8%.
B5: • Liquidity: Maintained adequate short-term solvency with Current Ratio at 2.09x and Quick Ratio at 1.18x in FY26, well above minimum safety thresholds.
B6: • Solvency: Conservative leverage with low Debt-to-Equity (0.11x) and strong Interest Coverage (20.38x) in FY26.
B7: • Valuation: Commands a premium multiple of 59.0x P/E, driven by category expansion expectations relative to peers.
B9: 2. Core Business Strengths | L9: s
B10: • Brand Equity: Strong domestic footprint in branded tea, salt, and packaged foods backed by the Tata group umbrella.
B11: • Balance Sheet Flexibility: Low debt levels allow internal funding for capex and targeted acquisitions without distress.
B12: • Pricing Power: Demonstrates operational capability to pass on raw material inflation to protect gross margins.
B14: 3. Key Risks & Areas of Concerns
B15: • Trailing Margins: Operating margins (14%) trail mature consumer peers such as Nestle (23%) and HUL (24%).
B16: • Rich Valuation: High P/E multiple (59.0x) leaves limited margin of safety if volume growth slows.
B17: • Input Volatility: Tea, coffee, and agricultural commodity cycles introduce periodic working capital fluctuations.
B19: 4. Final Investment Observation
B20: Tata Consumer is a high-quality, defensively positioned business with minimal leverage risk. While current valuation multiples price in substantial growth, continuous premiumization and product diversification support long-term compounding strength.

Sheet Working Capital
A1: Tata Consumer Products Ltd: Working Capital | H1: Days Sales Outstanding (DSO)=(Trade Receivables/Sales)*365
H2: Days Inventory Outstanding (DIO)=(Inventories /Expenses)*365
H3: Days Payable Outstanding (DPO)=(Trade Payables/Expenses)*365
A4: Metric / Formula | B4: FY 2022 | C4: FY 2023 | D4: FY 2024 | E4: FY 2025 | F4: FY 2026 | H4: Cash Conversion Cycle (CCC)=(DSO)+(DIO)+(DPO)
A5: Sales / Revenue (Cr) | B5: 12425 | C5: 13783 | D5: 15206 | E5: 17618 | F5: 20290
A6: Cost of Goods Sold (COGS) / Expenses (Cr) | B6: 10707 | C6: 11927 | D6: 12922 | E6: 15139 | F6: 17499
A7: Inventories (Cr) | B7: ='Raw Data'!B20 -> 2267 | C7: 2702 | D7: 2769 | E7: 3600 | F7: 3527
A8: Trade Receivables / Debtors (Cr) | B8: 835 | C8: 798 | D8: 897 | E8: 870 | F8: 1148
A9: Trade Payables / Creditors (Cr) | B9: 1916 | C9: 2348 | D9: 2707 | E9: 3508 | F9: 3875
A11: Days Sales Outstanding (DSO) | B11: =(B8/B5)*365 -> 24.529175 | C11: =(C8/C5)*365 -> 21.132555 | D11: =(D8/D5)*365 -> 21.531303 | E11: =(E8/E5)*365 -> 18.02418 | F11: =(F8/F5)*365 -> 20.651552
A12: Days Inventory Outstanding (DIO) | B12: =(B7/B6)*365 -> 77.281685 | C12: =(C7/C6)*365 -> 82.688857 | D12: =(D7/D6)*365 -> 78.214286 | E12: =(E7/E6)*365 -> 86.795693 | F12: =(F7/F6)*365 -> 73.567347
A13: Days Payable Outstanding (DPO) | B13: =(B9/B6)*365 -> 65.316148 | C13: =(C9/C6)*365 -> 71.855454 | D13: =(D9/D6)*365 -> 76.463009 | E13: =(E9/E6)*365 -> 84.577581 | F13: =(F9/F6)*365 -> 80.826047
A14: Cash Conversion Cycle (CCC) | B14: =B11+B12-B13 -> 36.494712 | C14: =C11+C12-C13 -> 31.965958 | D14: =D11+D12-D13 -> 23.28258 | E14: =E11+E12-E13 -> 20.242292 | F14: =F11+F12-F13 -> 13.392852
A16: Working Capital & Efficiency Insight: Tata Consumer substantially improved its working capital efficiency over the 5-year period, driving its Cash Conversion Cycle (CCC) down from ~36.5 days in FY22 to ~13.4 days in FY26. This positive trend was primarily fueled by expanding Days Payable Outstanding (DPO from 65.3 to 80.8 days)—effectively utilizing supplier credit terms to finance inventory—alongside faster customer receivables collection (DSO declining to 20.6 days).

Sheet DCF Valuation
A1: Tata Consumer Products Ltd: DCF Valuation
A3: 1.Model Assumptions
A5: Current Share Price (CMP) | B5: 983.2
A6: Shares Outstanding (Cr) | B6: 98.97
A7: Risk-Free Rate (Rf) | B7: 0.07
A8: Equity Risk Premium (ERP) | B8: 0.065
A9: Beta (β) | B9: 0.85
A10: Cost of Debt (Kd, post-tax) | B10: 0.06
A11: Weight of Equity (We) | B11: ='Peer Comparison'!B5/('Peer Comparison'!B5+'Raw Data'!F15) -> 0.97599795
A12: Weight of Debt (Wd) | B12: =1-B11 -> 0.024002047
A13: Weighted Average Cost of Capital (WACC) | B13: =(B7+B9*B8)*B11+(B10*B12) -> 0.12368387
A14: Terminal Growth Rate (g) | B14: 0.05
A16: 2.Historical & Forecast Free Cash Flow
A17: Cash Flow Projections (₹ in Cr)
A18: FY | B18: FY2024 | C18: FY2025 | D18: FY2026 | E18: FY2027 | F18: FY2028 | G18: FY2029 | H18: FY2030 | I18: FY2031
A19: Revenue / Sales | B19: ='Raw Data'!D6 -> 15206 | C19: ='Raw Data'!E6 -> 17618 | D19: ='Raw Data'!F6 -> 20290 | E19: =D19*(1+E20) -> 22724.8 | F19: =E19*(1+F20) -> 25224.528 | G19: =F19*(1+G20) -> 27746.981 | H19: =G19*(1+H20) -> 30244.209 | I19: =H19*(1+I20) -> 32663.746
A20: Revenue Growth Rate (%) | C20: =(C19-B19)/B19 -> 0.1586216 | D20: =(D19-C19)/C19 -> 0.15166307 | E20: 0.12 | F20: 0.11 | G20: 0.1 | H20: 0.09 | I20: 0.08
A21: EBIT (Operating Profit - D&A) | B21: ='Raw Data'!D10-'Raw Data'!D9 -> 1907 | C21: ='Raw Data'!E10-'Raw Data'!E9 -> 2102 | D21: ='Raw Data'!F10-'Raw Data'!F9 -> 2165 | E21: =E19*0.11 -> 2499.728 | F21: =F19*0.11 -> 2774.6981 | G21: =G19*0.11 -> 3052.1679 | H21: =H19*0.11 -> 3326.863 | I21: =I19*0.11 -> 3593.012
A22: Effective Tax Rate (%) | B22: 0.25 | C22: 0.25 | D22: 0.25 | E22: 0.25 | F22: 0.25 | G22: 0.25 | H22: 0.25 | I22: 0.25
A23: NOPAT (EBIT × (1 - Tax)) | B23: =B21*(1-B22) -> 1430.25 | C23: =C21*(1-C22) -> 1576.5 | D23: =D21*(1-D22) -> 1623.75 | E23: =E21*(1-E22) -> 1874.796 | F23: =F21*(1-F22) -> 2081.0236 | G23: =G21*(1-G22) -> 2289.1259 | H23: =H21*(1-H22) -> 2495.1472 | I23: =I21*(1-I22) -> 2694.759
A24: (+) Depreciation & Amortization | B24: ='Raw Data'!D9 -> 377 | C24: 377 | D24: 627 | E24: =E19*0.03 -> 681.744 | F24: =F19*0.03 -> 756.73584 | G24: =G19*0.03 -> 832.40942 | H24: =H19*0.03 -> 907.32627 | I24: =I19*0.03 -> 979.91237
A25: (-) Capital Expenditures (CapEx) | B25: 500 | C25: 550 | D25: 600 | E25: =E19*0.032 -> 727.1936 | F25: =F19*0.032 -> 807.1849 | G25: =G19*0.032 -> 887.90339 | H25: =H19*0.032 -> 967.81469 | I25: =I19*0.032 -> 1045.2399
A26: (-) Change in Working Capital (ΔNWC) | B26: 150 | C26: 180 | D26: 200 | E26: =E19*0.01 -> 227.248 | F26: =F19*0.01 -> 252.24528 | G26: =G19*0.01 -> 277.46981 | H26: =H19*0.01 -> 302.44209 | I26: =I19*0.01 -> 326.63746
A27: Free Cash Flow to Firm (FCFF) | B27: =B23+B24-B25-B26 -> 1157.25 | C27: =C23+C24-C25-C26 -> 1223.5 | D27: =D23+D24-D25-D26 -> 1450.75 | E27: =E23+E24-E25-E26 -> 1602.0984 | F27: =F23+F24-F25-F26 -> 1778.3292 | G27: =G23+G24-G25-G26 -> 1956.1621 | H27: =H23+H24-H25-H26 -> 2132.2167 | I27: =I23+I24-I25-I26 -> 2302.7941
A28: Discount Period (Years) | E28: 1 | F28: 2 | G28: 3 | H28: 4 | I28: 5
A29: Discount Factor [1 / (1 + WACC)^t] | E29: =1/(1+$B$13)^E28 -> 0.88993001 | F29: =1/(1+$B$13)^F28 -> 0.79197543 | G29: =1/(1+$B$13)^G28 -> 0.70480271 | H29: =1/(1+$B$13)^H28 -> 0.62722508 | I29: =1/(1+$B$13)^I28 -> 0.55818643
A30: Present Value of FCFF (PV) | E30: =E27*E29 -> 1425.7555 | F30: =F27*F29 -> 1408.3931 | G30: =G27*G29 -> 1378.7084 | H30: =H27*H29 -> 1337.3798 | I30: =I27*I29 -> 1285.3884
A32: 3.Valuation & Intrinsic Share Price
A33: Enterprise & Equity Valuation Summary
A34: Cumulative PV of 5-Yr Cash Flows | B34: =SUM(E30:I30) -> 6835.6251
A35: Terminal Value (TV) | B35: =(I27*(1+B14))/(B13-B14) -> 32814.969
A36: Present Value of Terminal Value (PV of TV) | B36: =B35*I29 -> 18316.87
A37: Enterprise Value (EV) | B37: =B34+B36 -> 25152.495
A38: (+) Cash & Cash Equivalents | B38: ='Raw Data'!F21 -> 3420
A39: (-) Total Debt | B39: ='Raw Data'!F15 -> 2393
A40: Equity Value (Implied) | B40: =B37+B38-B39 -> 26179.495
A41: Intrinsic Value Per Share (₹) | B41: =B40/B6 -> 264.5195
A42: Current Market Price (CMP) | B42: =B5 -> 983.2
A43: Analyst Recommendation (Upside / Downside %) | B43: =(B41-B42)/B42 -> -0.73096063
A45: DCF Valuation & Investment Thesis(Tata Consumer Products Ltd): 1. Valuation Summary: • Current Market Price (CMP): ₹983.20 • Implied Intrinsic Value per Share: ₹264.52 • Valuation Implication: Overvalued (~73% downside) • Discount Rate (WACC): 12.37% (Cost of Equity: 12.53%, Cost of Debt: 6.00%) • Terminal Growth Rate: 5.0% 2. Core Valuation Findings: Our 5-year DCF projection yields an Enterprise Value of ₹25,152.5 Cr and an Implied Equity Value of ₹26,179 Cr. After accounting for Net Cash (Cash of ₹3,420 Cr less Total Debt of ₹2,393 Cr), the intrinsic value equates to ₹264.52 per share versus the CMP of ₹983.20. 3. Investment Thesis & Analyst Verdict: Tata Consumer Products is significantly overvalued on an intrinsic cash-flow basis. The current market quotation (P/E ~59x) prices in exceptional perpetual growth and margin expansion well above its historical conversion profile. While the business displays consistent operational growth (10-12% revenue CAGR) and solid working-capital management (CCC of ~13.4 days), free cash flows cannot fundamentally justify the current multiple under a 12.4% hurdle rate. Conclusion: OVERVALUED / SELL (or HOLD for long-term defensive compounders, but not attractive for fresh capital deployment).
